{
  "$schema": "http://cyclonedx.org/schema/bom-1.4.schema.json",
  "bomFormat": "CycloneDX",
  "specVersion": "1.4",
  "serialNumber": "urn:uuid:7f60257a-cf55-4bf1-80ba-93b6f9a018e7",
  "version": 1,
  "metadata": {
    "timestamp": "2023-11-20T19:12:20.495697+00:00",
    "tools": [
      {
        "vendor": "CycloneDX",
        "name": "cyclonedx-bom",
        "version": "3.11.7"
      },
      {
        "vendor": "CycloneDX",
        "name": "cyclonedx-python-lib",
        "version": "3.1.5",
        "externalReferences": [
          {
            "url": "https://github.com/CycloneDX/cyclonedx-python-lib/actions",
            "type": "build-system"
          },
          {
            "url": "https://pypi.org/project/cyclonedx-python-lib/",
            "type": "distribution"
          },
          {
            "url": "https://cyclonedx.github.io/cyclonedx-python-lib/",
            "type": "documentation"
          },
          {
            "url": "https://github.com/CycloneDX/cyclonedx-python-lib/issues",
            "type": "issue-tracker"
          },
          {
            "url": "https://github.com/CycloneDX/cyclonedx-python-lib/blob/main/LICENSE",
            "type": "license"
          },
          {
            "url": "https://github.com/CycloneDX/cyclonedx-python-lib/blob/main/CHANGELOG.md",
            "type": "release-notes"
          },
          {
            "url": "https://github.com/CycloneDX/cyclonedx-python-lib",
            "type": "vcs"
          },
          {
            "url": "https://cyclonedx.org",
            "type": "website"
          }
        ]
      }
    ]
  },
  "components": [
    {
      "type": "library",
      "bom-ref": "a580d676-a376-4048-b7e4-8994621c32b7",
      "name": "PyYAML",
      "version": "6.0.1",
      "purl": "pkg:pypi/pyyaml@6.0.1"
    },
    {
      "type": "library",
      "bom-ref": "991a1548-6dce-4b84-ba25-a9aa0b4e83e7",
      "name": "foran",
      "version": "2023.6.19",
      "purl": "pkg:pypi/foran@2023.6.19"
    },
    {
      "type": "library",
      "bom-ref": "a959eac1-e348-40dd-b466-a7f9b32bc96f",
      "name": "shellingham",
      "version": "1.5.4",
      "purl": "pkg:pypi/shellingham@1.5.4"
    },
    {
      "type": "library",
      "bom-ref": "435394a8-829a-4b0f-98eb-0a1f95c4ae15",
      "name": "taksonomia",
      "version": "2023.6.18",
      "purl": "pkg:pypi/taksonomia@2023.6.18"
    },
    {
      "type": "library",
      "bom-ref": "c75e7fc2-3a3a-4930-b7b1-4de4c73f8295",
      "name": "treelib",
      "version": "1.7.0",
      "purl": "pkg:pypi/treelib@1.7.0"
    },
    {
      "type": "library",
      "bom-ref": "81ed87a0-feaa-41f2-94fe-d04bebfe9878",
      "name": "typer",
      "version": "0.9.0",
      "purl": "pkg:pypi/typer@0.9.0"
    }
  ],
  "dependencies": [
    {
      "ref": "a580d676-a376-4048-b7e4-8994621c32b7",
      "dependsOn": []
    },
    {
      "ref": "991a1548-6dce-4b84-ba25-a9aa0b4e83e7",
      "dependsOn": []
    },
    {
      "ref": "a959eac1-e348-40dd-b466-a7f9b32bc96f",
      "dependsOn": []
    },
    {
      "ref": "435394a8-829a-4b0f-98eb-0a1f95c4ae15",
      "dependsOn": []
    },
    {
      "ref": "c75e7fc2-3a3a-4930-b7b1-4de4c73f8295",
      "dependsOn": []
    },
    {
      "ref": "81ed87a0-feaa-41f2-94fe-d04bebfe9878",
      "dependsOn": []
    }
  ]
}
